kutt/cli.py
kutt/kutt.py
kutt-1.5.2.dist-info/LICENSE
kutt-1.5.2.dist-info/METADATA
kutt-1.5.2.dist-info/WHEEL
kutt-1.5.2.dist-info/entry_points.txt
kutt-1.5.2.dist-info/top_level.txt
kutt-1.5.2.dist-info/RECORD
